coinonepy/__init__.py
coinonepy/private.py
coinonepy/public.py
coinonpy-0.0.1.dist-info/LICENSE
coinonpy-0.0.1.dist-info/METADATA
coinonpy-0.0.1.dist-info/WHEEL
coinonpy-0.0.1.dist-info/top_level.txt
coinonpy-0.0.1.dist-info/RECORD
